ventaxiaiot/__init__.py
ventaxiaiot/__main__.py
ventaxiaiot/cli.py
ventaxiaiot/client.py
ventaxiaiot/commands.py
ventaxiaiot/messages.py
ventaxiaiot/pending_request_tracker.py
ventaxiaiot/schedule.py
ventaxiaiot/sentinel_kinetic.py
ventaxiaiot-0.1.9.dist-info/licenses/LICENSE
ventaxiaiot-0.1.9.dist-info/METADATA
ventaxiaiot-0.1.9.dist-info/WHEEL
ventaxiaiot-0.1.9.dist-info/entry_points.txt
ventaxiaiot-0.1.9.dist-info/top_level.txt
ventaxiaiot-0.1.9.dist-info/RECORD
