Metadata-Version: 2.4
Name: ventaxiaiot
Version: 0.1.9
Summary: Python API for controlling Vent-Axia IoT devices
Author: josyban
License: MIT
Requires-Python: >=3.13
License-File: LICENSE
Dynamic: license-file
